[
    {
        "name": "Looking for front end developer for just 1 homepage",
        "description": "I am looking for a landing page for my website, which needs to be developed in React and Tailwind CSS Only. I have two reference website that I linked. You need to design the page as per the colours in the logo. Can you do it? I will share. 1. Content 2. Reference website",
        "skills": [
            "React",
            "Tailwind"
        ],
        "location": "India",
        "isVarified": true,
        "proposals": 50,
        "spents": 1200,
        "budget": 30,
        "posted": "3 hours"
    },
    {
        "name": "Full Stack Developer needed for E-commerce Platform",
        "description": "We're building a comprehensive e-commerce platform with React frontend and Node.js backend. Looking for an experienced developer who can handle both frontend and backend development with modern best practices.",
        "skills": [
            "React",
            "Node.js",
            "MongoDB",
            "Express"
        ],
        "location": "Remote",
        "isVarified": true,
        "proposals": 23,
        "spents": 5000,
        "budget": 150,
        "posted": "1 day"
    },
    {
        "name": "Mobile App UI/UX Designer for Fintech Startup",
        "description": "Seeking a talented UI/UX designer to create intuitive and modern mobile app designs for our fintech application. Must have experience with financial applications and mobile-first design principles.",
        "skills": [
            "Figma",
            "UI/UX",
            "Mobile Design"
        ],
        "location": "USA",
        "isVarified": false,
        "proposals": 12,
        "spents": 800,
        "budget": 75,
        "posted": "2 days"
    },
    {
        "name": "Mobile App UI/UX Designer for Fintech Startup",
        "description": "Seeking a talented UI/UX designer to create intuitive and modern mobile app designs for our fintech application. Must have experience with financial applications and mobile-first design principles.",
        "skills": [
            "Figma",
            "UI/UX",
            "Mobile Design"
        ],
        "location": "USA",
        "isVarified": false,
        "proposals": 12,
        "spents": 800,
        "budget": 75,
        "posted": "2 days"
    },
    {
        "name": "Mobile App UI/UX Designer for Fintech Startup",
        "description": "Seeking a talented UI/UX designer to create intuitive and modern mobile app designs for our fintech application. Must have experience with financial applications and mobile-first design principles.",
        "skills": [
            "Figma",
            "UI/UX",
            "Mobile Design"
        ],
        "location": "USA",
        "isVarified": false,
        "proposals": 12,
        "spents": 800,
        "budget": 75,
        "posted": "2 days"
    },
    {
        "name": "Mobile App UI/UX Designer for Fintech Startup",
        "description": "Seeking a talented UI/UX designer to create intuitive and modern mobile app designs for our fintech application. Must have experience with financial applications and mobile-first design principles.",
        "skills": [
            "Figma",
            "UI/UX",
            "Mobile Design"
        ],
        "location": "USA",
        "isVarified": false,
        "proposals": 12,
        "spents": 800,
        "budget": 75,
        "posted": "2 days"
    },
    {
        "name": "Mobile App UI/UX Designer for Fintech Startup",
        "description": "Seeking a talented UI/UX designer to create intuitive and modern mobile app designs for our fintech application. Must have experience with financial applications and mobile-first design principles.",
        "skills": [
            "Figma",
            "UI/UX",
            "Mobile Design"
        ],
        "location": "USA",
        "isVarified": false,
        "proposals": 12,
        "spents": 800,
        "budget": 75,
        "posted": "2 days"
    },
    {
        "name": "Mobile App UI/UX Designer for Fintech Startup",
        "description": "Seeking a talented UI/UX designer to create intuitive and modern mobile app designs for our fintech application. Must have experience with financial applications and mobile-first design principles.",
        "skills": [
            "Figma",
            "UI/UX",
            "Mobile Design"
        ],
        "location": "USA",
        "isVarified": false,
        "proposals": 12,
        "spents": 800,
        "budget": 75,
        "posted": "2 days"
    },
    {
        "name": "Mobile App UI/UX Designer for Fintech Startup",
        "description": "Seeking a talented UI/UX designer to create intuitive and modern mobile app designs for our fintech application. Must have experience with financial applications and mobile-first design principles.",
        "skills": [
            "Figma",
            "UI/UX",
            "Mobile Design"
        ],
        "location": "USA",
        "isVarified": false,
        "proposals": 12,
        "spents": 800,
        "budget": 75,
        "posted": "2 days"
    },
    {
        "name": "Mobile App UI/UX Designer for Fintech Startup",
        "description": "Seeking a talented UI/UX designer to create intuitive and modern mobile app designs for our fintech application. Must have experience with financial applications and mobile-first design principles.",
        "skills": [
            "Figma",
            "UI/UX",
            "Mobile Design"
        ],
        "location": "USA",
        "isVarified": false,
        "proposals": 12,
        "spents": 800,
        "budget": 75,
        "posted": "2 days"
    },
    {
        "name": "Mobile App UI/UX Designer for Fintech Startup",
        "description": "Seeking a talented UI/UX designer to create intuitive and modern mobile app designs for our fintech application. Must have experience with financial applications and mobile-first design principles.",
        "skills": [
            "Figma",
            "UI/UX",
            "Mobile Design"
        ],
        "location": "USA",
        "isVarified": false,
        "proposals": 12,
        "spents": 800,
        "budget": 75,
        "posted": "2 days"
    },
    {
        "name": "Mobile App UI/UX Designer for Fintech Startup",
        "description": "Seeking a talented UI/UX designer to create intuitive and modern mobile app designs for our fintech application. Must have experience with financial applications and mobile-first design principles.",
        "skills": [
            "Figma",
            "UI/UX",
            "Mobile Design"
        ],
        "location": "USA",
        "isVarified": false,
        "proposals": 12,
        "spents": 800,
        "budget": 75,
        "posted": "2 days"
    },
    {
        "name": "Mobile App UI/UX Designer for Fintech Startup",
        "description": "Seeking a talented UI/UX designer to create intuitive and modern mobile app designs for our fintech application. Must have experience with financial applications and mobile-first design principles.",
        "skills": [
            "Figma",
            "UI/UX",
            "Mobile Design"
        ],
        "location": "USA",
        "isVarified": false,
        "proposals": 12,
        "spents": 800,
        "budget": 75,
        "posted": "2 days"
    },
    {
        "name": "Mobile App UI/UX Designer for Fintech Startup",
        "description": "Seeking a talented UI/UX designer to create intuitive and modern mobile app designs for our fintech application. Must have experience with financial applications and mobile-first design principles.",
        "skills": [
            "Figma",
            "UI/UX",
            "Mobile Design"
        ],
        "location": "USA",
        "isVarified": false,
        "proposals": 12,
        "spents": 800,
        "budget": 75,
        "posted": "2 days"
    },
    {
        "name": "Mobile App UI/UX Designer for Fintech Startup",
        "description": "Seeking a talented UI/UX designer to create intuitive and modern mobile app designs for our fintech application. Must have experience with financial applications and mobile-first design principles.",
        "skills": [
            "Figma",
            "UI/UX",
            "Mobile Design"
        ],
        "location": "USA",
        "isVarified": false,
        "proposals": 12,
        "spents": 800,
        "budget": 75,
        "posted": "2 days"
    },
    {
        "name": "Mobile App UI/UX Designer for Fintech Startup",
        "description": "Seeking a talented UI/UX designer to create intuitive and modern mobile app designs for our fintech application. Must have experience with financial applications and mobile-first design principles.",
        "skills": [
            "Figma",
            "UI/UX",
            "Mobile Design"
        ],
        "location": "USA",
        "isVarified": false,
        "proposals": 12,
        "spents": 800,
        "budget": 75,
        "posted": "2 days"
    },
    {
        "name": "Mobile App UI/UX Designer for Fintech Startup",
        "description": "Seeking a talented UI/UX designer to create intuitive and modern mobile app designs for our fintech application. Must have experience with financial applications and mobile-first design principles.",
        "skills": [
            "Figma",
            "UI/UX",
            "Mobile Design"
        ],
        "location": "USA",
        "isVarified": false,
        "proposals": 12,
        "spents": 800,
        "budget": 75,
        "posted": "2 days"
    },
    {
        "name": "Mobile App UI/UX Designer for Fintech Startup",
        "description": "Seeking a talented UI/UX designer to create intuitive and modern mobile app designs for our fintech application. Must have experience with financial applications and mobile-first design principles.",
        "skills": [
            "Figma",
            "UI/UX",
            "Mobile Design"
        ],
        "location": "USA",
        "isVarified": false,
        "proposals": 12,
        "spents": 800,
        "budget": 75,
        "posted": "2 days"
    },
    {
        "name": "Mobile App UI/UX Designer for Fintech Startup",
        "description": "Seeking a talented UI/UX designer to create intuitive and modern mobile app designs for our fintech application. Must have experience with financial applications and mobile-first design principles.",
        "skills": [
            "Figma",
            "UI/UX",
            "Mobile Design"
        ],
        "location": "USA",
        "isVarified": false,
        "proposals": 12,
        "spents": 800,
        "budget": 75,
        "posted": "2 days"
    },
    {
        "name": "Mobile App UI/UX Designer for Fintech Startup",
        "description": "Seeking a talented UI/UX designer to create intuitive and modern mobile app designs for our fintech application. Must have experience with financial applications and mobile-first design principles.",
        "skills": [
            "Figma",
            "UI/UX",
            "Mobile Design"
        ],
        "location": "USA",
        "isVarified": false,
        "proposals": 12,
        "spents": 800,
        "budget": 75,
        "posted": "2 days"
    },
    {
        "name": "Mobile App UI/UX Designer for Fintech Startup",
        "description": "Seeking a talented UI/UX designer to create intuitive and modern mobile app designs for our fintech application. Must have experience with financial applications and mobile-first design principles.",
        "skills": [
            "Figma",
            "UI/UX",
            "Mobile Design"
        ],
        "location": "USA",
        "isVarified": false,
        "proposals": 12,
        "spents": 800,
        "budget": 75,
        "posted": "2 days"
    },
    {
        "name": "Mobile App UI/UX Designer for Fintech Startup",
        "description": "Seeking a talented UI/UX designer to create intuitive and modern mobile app designs for our fintech application. Must have experience with financial applications and mobile-first design principles.",
        "skills": [
            "Figma",
            "UI/UX",
            "Mobile Design"
        ],
        "location": "USA",
        "isVarified": false,
        "proposals": 12,
        "spents": 800,
        "budget": 75,
        "posted": "2 days"
    }
]